{
  "parent": "block/block",
  "textures": {
    "stand": "minecraft:block/smooth_stone",
    "particle": "minecraft:block/smooth_stone"
  },
  "elements": [
    {
      "from": [3, 0, 3],
      "to": [13, 1, 13],
      "faces": {
        "up": { "texture": "#stand" },
        "down": { "texture": "#stand", "cullface": "down" },
        "north": { "texture": "#stand" },
        "east": { "texture": "#stand" },
        "south": { "texture": "#stand" },
        "west": { "texture": "#stand" }
      }
    },
    {
      "from": [7, 1, 7],
      "to": [9, 16, 9],
      "faces": {
        "north": { "texture": "#stand" },
        "east": { "texture": "#stand" },
        "south": { "texture": "#stand" },
        "west": { "texture": "#stand" }
      }
    }
  ]
}
