{
  "parent": "minecraft:recipes/root",
  "rewards": {
    "recipes": [
      "adorn:byg/cherry_chair"
    ]
  },
  "criteria": {
    "has_key_item_0": {
      "trigger": "minecraft:inventory_changed",
      "conditions": {
        "items": [
          {
            "items": [
              "byg:cherry_slab"
            ]
          }
        ]
      }
    },
    "has_the_recipe": {
      "trigger": "minecraft:recipe_unlocked",
      "conditions": {
        "recipe": "adorn:byg/cherry_chair"
      }
    }
  },
  "requirements": [
    [
      "has_key_item_0",
      "has_the_recipe"
    ]
  ]
}
