{
  "parent": "minecraft:recipes/root",
  "rewards": {
    "recipes": [
      "adorn:byg/red_rock_platform"
    ]
  },
  "criteria": {
    "has_slab": {
      "trigger": "minecraft:inventory_changed",
      "conditions": {
        "items": [
          {
            "items": [
              "byg:red_rock_slab"
            ]
          }
        ]
      }
    },
    "has_the_recipe": {
      "trigger": "minecraft:recipe_unlocked",
      "conditions": {
        "recipe": "adorn:byg/red_rock_platform"
      }
    }
  },
  "requirements": [
    [
      "has_slab",
      "has_the_recipe"
    ]
  ],
  "conditions": [
    {
      "type": "forge:mod_loaded",
      "modid": "byg"
    }
  ]

}
